ha/__init__.py
ha/dataset.py
ha/vendors.py
ha-0.0.9.dist-info/licenses/LICENSE
ha-0.0.9.dist-info/METADATA
ha-0.0.9.dist-info/WHEEL
ha-0.0.9.dist-info/top_level.txt
ha-0.0.9.dist-info/RECORD
