Metadata-Version: 2.4
Name: ha
Version: 0.0.9
Summary: joke tools
Home-page: https://github.com/t-c-w/ha
Author: Thor Whalen
License: mit
Platform: any
License-File: LICENSE
Requires-Dist: dol
Requires-Dist: graze
Requires-Dist: config2py
Provides-Extra: optional-deps
Requires-Dist: laugh; extra == "optional-deps"
Requires-Dist: pyjokes; extra == "optional-deps"
Dynamic: license-file
